ctparse/__init__.py
ctparse/corpus.py
ctparse/count_vectorizer.py
ctparse/ctparse.py
ctparse/loader.py
ctparse/nb_estimator.py
ctparse/nb_scorer.py
ctparse/partial_parse.py
ctparse/pipeline.py
ctparse/py.typed
ctparse/rule.py
ctparse/scorer.py
ctparse/timers.py
ctparse/types.py
ctparse/models/model.pbz
ctparse/time/__init__.py
ctparse/time/auto_corpus.py
ctparse/time/corpus.py
ctparse/time/postprocess_latent.py
ctparse/time/rules.py
ctparse-0.3.6.dist-info/AUTHORS.rst
ctparse-0.3.6.dist-info/LICENSE
ctparse-0.3.6.dist-info/METADATA
ctparse-0.3.6.dist-info/WHEEL
ctparse-0.3.6.dist-info/top_level.txt
ctparse-0.3.6.dist-info/RECORD
