Metadata-Version: 2.1
Name: ctparse
Version: 0.3.6
Summary: Parse natural language time expressions in python
Home-page: https://github.com/comtravo/ctparse
Author: Sebastian Mika/Comtravo
Author-email: sebastian.mika@comtravo.com
License: MIT license
Keywords: ctparse time parsing natural language
Classifier: Development Status :: 3 - Alpha
Classifier: Intended Audience :: Developers
Classifier: License :: OSI Approved :: MIT License
Classifier: Natural Language :: English
Classifier: Programming Language :: Python :: 3
Classifier: Programming Language :: Python :: 3.7
Classifier: Programming Language :: Python :: 3.8
Classifier: Programming Language :: Python :: 3.9
Classifier: Topic :: Software Development :: Libraries :: Python Modules
Classifier: Topic :: Text Processing :: Linguistic
License-File: LICENSE
License-File: AUTHORS.rst
Requires-Dist: python-dateutil (<3.0.0,>=2.7.3)
Requires-Dist: regex (>=2018.6.6)
Requires-Dist: tqdm (<5.0.0,>=4.23.4)
